uron/VERSION
uron/__init__.py
uron-0.0.0.dev20230226.dist-info/LICENSE
uron-0.0.0.dev20230226.dist-info/METADATA
uron-0.0.0.dev20230226.dist-info/WHEEL
uron-0.0.0.dev20230226.dist-info/top_level.txt
uron-0.0.0.dev20230226.dist-info/RECORD
