Metadata-Version: 2.1
Name: uron
Version: 0.0.0.dev20230226
Summary: A python library to run code with different venvs or package versions
Author-email: Yan Zhang <dev.claude.yan.zhang@gmail.com>
License: MIT License
Project-URL: Homepage, https://github.com/claudezss/uron
Project-URL: Bug Tracker, https://github.com/claudezss/uron/issues
Keywords: venv,python,package
Classifier: Development Status :: 3 - Alpha
Classifier: Programming Language :: Python :: 3
Classifier: License :: OSI Approved :: MIT License
Classifier: Operating System :: OS Independent
Classifier: Topic :: Software Development :: Libraries
Requires-Python: >=3.7
License-File: LICENSE
Provides-Extra: dev
Requires-Dist: pre-commit ; extra == 'dev'
Requires-Dist: pytest (>=7.0.0) ; extra == 'dev'
Requires-Dist: pytest-cov ; extra == 'dev'
